CHANGES.txt
LICENSE.txt
Makefile
README.txt
TODO.txt
bootstrap.py
buildout.cfg
ez_setup.py
setup.cfg
setup.py
src/xanalogica/__init__.py
src/xanalogica.tumbler.egg-info/PKG-INFO
src/xanalogica.tumbler.egg-info/SOURCES.txt
src/xanalogica.tumbler.egg-info/dependency_links.txt
src/xanalogica.tumbler.egg-info/namespace_packages.txt
src/xanalogica.tumbler.egg-info/requires.txt
src/xanalogica.tumbler.egg-info/top_level.txt
src/xanalogica.tumbler.egg-info/zip-safe
src/xanalogica/tumbler/Tumblers.txt
src/xanalogica/tumbler/__init__.py
src/xanalogica/tumbler/tests.py