Metadata-Version: 1.0
Name: xanalogica.tumbler
Version: 0.2dev
Summary: Flexible general-purpose coordinate elements with properties of integers and tuples.
Home-page: http://www.python.org/pypi/xanalogica.tumbler
Author: Jeff Rush
Author-email: jeff@taupro.com
License: GPL 3
Keywords: xanalogica,tumblers
Platform: UNKNOWN
Classifier: Development Status :: 2 - Pre-Alpha
Classifier: Intended Audience :: Developers
Classifier: License :: OSI Approved :: GNU General Public License (GPL)
Classifier: Operating System :: OS Independent
Classifier: Programming Language :: Python
Classifier: Topic :: Software Development :: Libraries :: Python Modules
